LICENSE
MANIFEST.in
README
setup.cfg
setup.py
Flask_AutoIndex.egg-info/PKG-INFO
Flask_AutoIndex.egg-info/SOURCES.txt
Flask_AutoIndex.egg-info/dependency_links.txt
Flask_AutoIndex.egg-info/entry_points.txt
Flask_AutoIndex.egg-info/not-zip-safe
Flask_AutoIndex.egg-info/requires.txt
Flask_AutoIndex.egg-info/top_level.txt
docs/conf.py
docs/index.rst
docs/_static/example.png
docs/_static/flask-autoindex.png
flask_autoindex/__init__.py
flask_autoindex/entry.py
flask_autoindex/icons.py
flask_autoindex/run.py
flask_autoindex/static/asc.gif
flask_autoindex/static/autoindex.css
flask_autoindex/static/desc.gif
flask_autoindex/templates/__autoindex__/autoindex.html
flask_autoindex/templates/__autoindex__/macros.html
tests/__init__.py
tests/blueprinttest/__init__.py
tests/static/helloworld.txt
tests/static/test.7z
tests/static/test.ai
tests/static/test.alz
tests/static/test.app
tests/static/test.applescript
tests/static/test.asp
tests/static/test.avi
tests/static/test.bak
tests/static/test.bat
tests/static/test.bin
tests/static/test.bmp
tests/static/test.bup
tests/static/test.c
tests/static/test.cab
tests/static/test.cer
tests/static/test.cfg
tests/static/test.cgi
tests/static/test.com
tests/static/test.conf
tests/static/test.cpl
tests/static/test.cpp
tests/static/test.css
tests/static/test.csv
tests/static/test.cur
tests/static/test.db
tests/static/test.dll
tests/static/test.dmg
tests/static/test.doc
tests/static/test.docx
tests/static/test.eps
tests/static/test.exe
tests/static/test.fla
tests/static/test.flv
tests/static/test.gif
tests/static/test.h
tests/static/test.htm
tests/static/test.html
tests/static/test.hwp
tests/static/test.ico
tests/static/test.ics
tests/static/test.ini
tests/static/test.iso
tests/static/test.jar
tests/static/test.java
tests/static/test.jpeg
tests/static/test.jpg
tests/static/test.js
tests/static/test.json
tests/static/test.jsp
tests/static/test.less
tests/static/test.log
tests/static/test.markdown
tests/static/test.md
tests/static/test.mid
tests/static/test.mov
tests/static/test.mp3
tests/static/test.mp4
tests/static/test.mpa
tests/static/test.mpeg
tests/static/test.mpg
tests/static/test.pdf
tests/static/test.php
tests/static/test.pkg
tests/static/test.png
tests/static/test.ppt
tests/static/test.pptx
